spacy_diffbot_nlapi/__init__.py
spacy_diffbot_nlapi/nlapi.py
spacy_diffbot_nlapi-1.1.0.dist-info/LICENSE
spacy_diffbot_nlapi-1.1.0.dist-info/METADATA
spacy_diffbot_nlapi-1.1.0.dist-info/WHEEL
spacy_diffbot_nlapi-1.1.0.dist-info/top_level.txt
spacy_diffbot_nlapi-1.1.0.dist-info/RECORD
