Metadata-Version: 2.1
Name: spacy-diffbot-nlapi
Version: 1.1.0
Summary: spaCy wrapper for Diffbot Natural Language API
Home-page: https://github.com/diffbot/spacy-diffbot-nlapi
Author: Jay Schmidek
Author-email: jay@diffbot.com
License: MIT
Keywords: Diffbot,Natural Language API
Platform: UNKNOWN
Requires-Python: >=3.6
Requires-Dist: spacy (>=3)
Requires-Dist: aiohttp (>=3.7)
